empythy/EmpathyMachines.py
empythy/__init__.py
empythy/test_script.py
empythy/utils.py
empythy/corpora/aggregatedCorpusCleanedAndFiltered.csv
empythy-1.0.0.dist-info/DESCRIPTION.rst
empythy-1.0.0.dist-info/METADATA
empythy-1.0.0.dist-info/RECORD
empythy-1.0.0.dist-info/WHEEL
empythy-1.0.0.dist-info/metadata.json
empythy-1.0.0.dist-info/top_level.txt
