Metadata-Version: 2.0
Name: empythy
Version: 1.0.0
Summary: An off-the-rack NLP sentiment classifier- upload your own corpus or use the pre-installed ones
Home-page: https://github.com/ClimbsRocks/EmpathyMachines
Author: Preston Parry
Author-email: ClimbsBytes@gmail.com
License: MIT
Keywords: machine learning,data science,NLP,natural language processing,sentiment,sentiment analysis,sentiment prediction,twitter corpus,twitter,tweets corpus,movie reviews corpus,NLTK,automated machine learning
Platform: UNKNOWN
Classifier: Development Status :: 4 - Beta
Classifier: Intended Audience :: Developers
Classifier: Topic :: Scientific/Engineering :: Artificial Intelligence
Classifier: License :: OSI Approved :: MIT License
Classifier: Programming Language :: Python :: 2
Classifier: Programming Language :: Python :: 2.7
Classifier: Programming Language :: Python :: 3
Classifier: Programming Language :: Python :: 3.5
Requires-Dist: nltk
Requires-Dist: scikit-learn
